knighted/__init__.py
knighted/_version.py
knighted/bases.py
knighted-0.3.dist-info/LICENSE
knighted-0.3.dist-info/METADATA
knighted-0.3.dist-info/WHEEL
knighted-0.3.dist-info/top_level.txt
knighted-0.3.dist-info/RECORD
